polymarket_trader/__init__.py
polymarket_trader/__main__.py
polymarket_trader/cli.py
polymarket_trader/client.py
polymarket_trader/config.py
polymarket_trader-0.2.1.dist-info/METADATA
polymarket_trader-0.2.1.dist-info/WHEEL
polymarket_trader-0.2.1.dist-info/entry_points.txt
polymarket_trader-0.2.1.dist-info/licenses/LICENSE
polymarket_trader-0.2.1.dist-info/RECORD
