Metadata-Version: 2.4
Name: polymarket-trader
Version: 0.2.1
Summary: Polymarket CLOB trading CLI
License: MIT License
License-File: LICENSE
Keywords: cli,clob,polymarket,prediction-market,trading
Classifier: Development Status :: 3 - Alpha
Classifier: Environment :: Console
Classifier: Intended Audience :: Developers
Classifier: License :: OSI Approved :: MIT License
Classifier: Programming Language :: Python :: 3
Classifier: Programming Language :: Python :: 3 :: Only
Classifier: Programming Language :: Python :: 3.10
Classifier: Programming Language :: Python :: 3.11
Classifier: Programming Language :: Python :: 3.12
Classifier: Topic :: Office/Business :: Financial
Classifier: Topic :: Utilities
Requires-Python: >=3.10
Requires-Dist: py-clob-client
